{"version":1,"resource":"vscode-remote://ssh-remote%2B147.96.81.119/home/estudiante/monitoring/spark-history-server-deployment.yaml","entries":[{"id":"mc7q.yaml","timestamp":1692380944992},{"id":"6zzi.yaml","timestamp":1692381067829},{"id":"OwN8.yaml","timestamp":1692381209507},{"id":"9RaL.yaml","timestamp":1692381705413},{"id":"yl7d.yaml","timestamp":1692381863739},{"id":"jFbg.yaml","timestamp":1692382122278},{"id":"2Rs6.yaml","timestamp":1692382320881},{"id":"zhnf.yaml","timestamp":1692382449374},{"id":"Jy81.yaml","timestamp":1692382656669},{"id":"QsWS.yaml","timestamp":1692383207371},{"id":"dGMy.yaml","timestamp":1692609162831},{"id":"8KCn.yaml","timestamp":1692609561261},{"id":"62mF.yaml","timestamp":1692609653510},{"id":"9qUy.yaml","timestamp":1692610310291}]}